static_data_dp/DataStore.py
static_data_dp/__init__.py
static_data_dp/ddragon.py
static_data_dp/patch.py
static_data_dp-0.1.1.dist-info/LICENSE
static_data_dp-0.1.1.dist-info/METADATA
static_data_dp-0.1.1.dist-info/WHEEL
static_data_dp-0.1.1.dist-info/top_level.txt
static_data_dp-0.1.1.dist-info/RECORD
