Metadata-Version: 2.1
Name: static-data-dp
Version: 0.1.1
Summary: Library to easily handles ddragon ressources files for League of Legends, origined by Canisback, modified by dp0973
Home-page: https://github.com/dp0973/static-data
Author: dp0973
Author-email: yeong0973@gmail.com
License: UNKNOWN
Keywords: Riot API,python,static-data
Platform: UNKNOWN
License-File: LICENSE
Requires-Dist: requests
Requires-Dist: asyncio
Requires-Dist: aiohttp
